src/math/cmult.sv
// ============================================================================
// File:        cmult.sv
// Description: Fully pipelined fixed-point complex multiplier (A * B).
//              Latency: 3 clock cycles.
// ============================================================================

`timescale 1ns / 1ps

module cmult #(
    parameter int WIDTH     = 16,   // Total bit width
    parameter int FRAC_BITS = 15,   // Number of fractional bits (e.g., Q1.15)
    parameter bit SATURATE  = 1'b1  // 1: Enable overflow saturation, 0: Truncate
) (
    input logic clk,
    input logic rst_n, // Active-low synchronous reset

    // Control
    input  logic valid_in,
    output logic valid_out,

    // Operands: A = a_re + j*a_im, B = b_re + j*b_im
    input logic signed [WIDTH-1:0] a_re,
    input logic signed [WIDTH-1:0] a_im,
    input logic signed [WIDTH-1:0] b_re,
    input logic signed [WIDTH-1:0] b_im,

    // Product: P = p_re + j*p_im
    output logic signed [WIDTH-1:0] p_re,
    output logic signed [WIDTH-1:0] p_im
);

  localparam int PROD_WIDTH = 2 * WIDTH;
  localparam logic signed [WIDTH-1:0] MAX_POS = {1'b0, {(WIDTH - 1) {1'b1}}};
  localparam logic signed [WIDTH-1:0] MAX_NEG = {1'b1, {(WIDTH - 1) {1'b0}}};

  // ------------------------------------------------------------------------
  // Pipeline Stage 1: Input Registration
  // ------------------------------------------------------------------------
  logic signed [WIDTH-1:0] a_re_r, a_im_r;
  logic signed [WIDTH-1:0] b_re_r, b_im_r;
  logic vld_pipe_1;

  always_ff @(posedge clk) begin
    if (!rst_n) begin
      a_re_r     <= '0;
      a_im_r     <= '0;
      b_re_r     <= '0;
      b_im_r     <= '0;
      vld_pipe_1 <= 1'b0;
    end else begin
      a_re_r     <= a_re;
      a_im_r     <= a_im;
      b_re_r     <= b_re;
      b_im_r     <= b_im;
      vld_pipe_1 <= valid_in;
    end
  end

  // ------------------------------------------------------------------------
  // Pipeline Stage 2: 4 Multiplications (dsp-inferable)
  // ------------------------------------------------------------------------
  logic signed [PROD_WIDTH-1:0] m_rr, m_ii, m_ri, m_ir;
  logic vld_pipe_2;

  always_ff @(posedge clk) begin
    if (!rst_n) begin
      m_rr       <= '0;
      m_ii       <= '0;
      m_ri       <= '0;
      m_ir       <= '0;
      vld_pipe_2 <= 1'b0;
    end else begin
      m_rr       <= a_re_r * b_re_r;
      m_ii       <= a_im_r * b_im_r;
      m_ri       <= a_re_r * b_im_r;
      m_ir       <= a_im_r * b_re_r;
      vld_pipe_2 <= vld_pipe_1;
    end
  end

  // ------------------------------------------------------------------------
  // Pipeline Stage 3: Add/Subtract, Rounding, and Saturation
  // ------------------------------------------------------------------------
  logic signed [PROD_WIDTH:0] sum_re, sum_im;  // 1 bit extra for add/sub
  logic signed [PROD_WIDTH:0] rnd_re, rnd_im;

  // Subtraction and Addition
  always_comb begin
    sum_re = (PROD_WIDTH + 1)'(m_rr) - (PROD_WIDTH + 1)'(m_ii);
    sum_im = (PROD_WIDTH + 1)'(m_ri) + (PROD_WIDTH + 1)'(m_ir);

    // Add rounding offset: 2^(FRAC_BITS - 1)
    if (FRAC_BITS > 0) begin
      rnd_re = sum_re + ((PROD_WIDTH + 1)'(1) << (FRAC_BITS - 1));
      rnd_im = sum_im + ((PROD_WIDTH + 1)'(1) << (FRAC_BITS - 1));
    end else begin
      rnd_re = sum_re;
      rnd_im = sum_im;
    end
  end

  // Saturation and Output Register
  function automatic logic signed [WIDTH-1:0] saturate_and_slice(
      input logic signed [PROD_WIDTH:0] val);
    logic signed [PROD_WIDTH - FRAC_BITS:0] shifted;
    shifted = val >>> FRAC_BITS;

    if (SATURATE) begin
      if (shifted > (PROD_WIDTH - FRAC_BITS + 1)'(MAX_POS)) begin
        return MAX_POS;
      end else if (shifted < (PROD_WIDTH - FRAC_BITS + 1)'(MAX_NEG)) begin
        return MAX_NEG;
      end else begin
        return shifted[WIDTH-1:0];
      end
    end else begin
      return shifted[WIDTH-1:0];
    end
  endfunction

  always_ff @(posedge clk) begin
    if (!rst_n) begin
      p_re      <= '0;
      p_im      <= '0;
      valid_out <= 1'b0;
    end else begin
      p_re      <= saturate_and_slice(rnd_re);
      p_im      <= saturate_and_slice(rnd_im);
      valid_out <= vld_pipe_2;
    end
  end

endmodule

sim/tb_cmult.sv
// ============================================================================
// File:        tb_cmult.sv
// Description: Icarus Verilog-friendly self-checking unit testbench for cmult.sv
// ============================================================================

`timescale 1ns / 1ps

module tb_cmult;

  localparam int WIDTH = 16;
  localparam int FRAC_BITS = 15;
  localparam int CLK_PER = 10;  // 100 MHz
  localparam real SCALE = 32768.0;  // 2^15
  localparam int FIFO_DEPTH = 64;

  logic clk;
  logic rst_n;
  logic valid_in;
  logic valid_out;
  logic signed [WIDTH-1:0] a_re, a_im;
  logic signed [WIDTH-1:0] b_re, b_im;
  logic signed [WIDTH-1:0] p_re, p_im;

  // Instantiate DUT
  cmult #(
      .WIDTH    (WIDTH),
      .FRAC_BITS(FRAC_BITS),
      .SATURATE (1'b1)
  ) dut (
      .clk      (clk),
      .rst_n    (rst_n),
      .valid_in (valid_in),
      .valid_out(valid_out),
      .a_re     (a_re),
      .a_im     (a_im),
      .b_re     (b_re),
      .b_im     (b_im),
      .p_re     (p_re),
      .p_im     (p_im)
  );

  // Waveform dumping for Surfer / Icarus
`ifdef DUMP_FILE
  initial begin
    $dumpfile(`DUMP_FILE);
    $dumpvars(0, tb_cmult);
  end
`endif

  // Clock generator
  initial begin
    clk = 0;
    forever #(CLK_PER / 2) clk = ~clk;
  end

  // Verification Scoreboard using flat circular arrays (Icarus compatible)
  real exp_re_fifo[0:FIFO_DEPTH-1];
  real exp_im_fifo[0:FIFO_DEPTH-1];
  int wr_ptr = 0;
  int rd_ptr = 0;
  int fifo_count = 0;

  int error_count = 0;
  int test_count = 0;

  // Convert integer fixed-point to real
  function automatic real to_real(input logic signed [WIDTH-1:0] val);
    return $itor(val) / SCALE;
  endfunction

  // Task to push expected values into circular FIFO
  task automatic push_expected(input real re_val, input real im_val);
    begin
      exp_re_fifo[wr_ptr] = re_val;
      exp_im_fifo[wr_ptr] = im_val;
      wr_ptr = (wr_ptr + 1) % FIFO_DEPTH;
      fifo_count = fifo_count + 1;
    end
  endtask

  // Task to drive stimulus and calculate expected outputs
  task automatic drive_sample(input real ar, input real ai, input real br, input real bi);
    real target_re, target_im;
    begin
      @(posedge clk);
      valid_in <= 1'b1;
      a_re     <= $rtoi(ar * SCALE);
      a_im     <= $rtoi(ai * SCALE);
      b_re     <= $rtoi(br * SCALE);
      b_im     <= $rtoi(bi * SCALE);

      // Floating-point ideal calculation
      target_re = (ar * br) - (ai * bi);
      target_im = (ar * bi) + (ai * br);

      // Clamping to match saturation limits [-1.0, +0.999969]
      if (target_re > (32767.0 / SCALE)) target_re = 32767.0 / SCALE;
      if (target_re < -1.0) target_re = -1.0;

      if (target_im > (32767.0 / SCALE)) target_im = 32767.0 / SCALE;
      if (target_im < -1.0) target_im = -1.0;

      push_expected(target_re, target_im);
    end
  endtask

  // Output monitor & checker process
  initial begin
    real actual_re, actual_im;
    real expected_re, expected_im;
    real diff_re, diff_im;

    forever
    @(posedge clk) begin
      if (rst_n && valid_out) begin
        if (fifo_count == 0) begin
          $display("[TB ERROR] Received unexpected valid_out at time %0t!", $time);
          error_count = error_count + 1;
        end else begin
          expected_re = exp_re_fifo[rd_ptr];
          expected_im = exp_im_fifo[rd_ptr];
          rd_ptr = (rd_ptr + 1) % FIFO_DEPTH;
          fifo_count = fifo_count - 1;

          actual_re = to_real(p_re);
          actual_im = to_real(p_im);

          diff_re = (actual_re > expected_re) ? (actual_re - expected_re) : (expected_re - actual_re);
          diff_im = (actual_im > expected_im) ? (actual_im - expected_im) : (expected_im - actual_im);

          // Allow up to 1.5 LSBs of tolerance due to fixed-point rounding
          if (diff_re > (1.5 / SCALE) || diff_im > (1.5 / SCALE)) begin
            $display("[MISMATCH] Sample %0d: Expected (%f, %f), Got (%f, %f)", test_count,
                     expected_re, expected_im, actual_re, actual_im);
            error_count = error_count + 1;
          end
          test_count = test_count + 1;
        end
      end
    end
  end

  // Stimulus process
  int i;
  initial begin
    valid_in = 1'b0;
    a_re     = '0;
    a_im     = '0;
    b_re     = '0;
    b_im     = '0;
    rst_n    = 1'b0;

    // Apply Reset
    #(CLK_PER * 5);
    rst_n = 1'b1;
    #(CLK_PER * 2);

    $display("--- Starting Corner Case Tests ---");
    drive_sample(0.0, 0.0, 0.5, -0.5);
    drive_sample(0.75, -0.25, 0.9999, 0.0);
    drive_sample(0.5, 0.3, 0.0, 0.9999);
    drive_sample(-1.0, 0.0, -1.0, 0.0);  // Saturation test: -1 * -1

    @(posedge clk);
    valid_in <= 1'b0;
    #(CLK_PER * 5);  // Allow pipeline to drain

    $display("--- Starting Random Stress Tests (1000 vectors) ---");
    for (i = 0; i < 1000; i = i + 1) begin
      real r_ar, r_ai, r_br, r_bi;
      r_ar = $itor($urandom_range(0, 65535) - 32768) / 32768.0;
      r_ai = $itor($urandom_range(0, 65535) - 32768) / 32768.0;
      r_br = $itor($urandom_range(0, 65535) - 32768) / 32768.0;
      r_bi = $itor($urandom_range(0, 65535) - 32768) / 32768.0;
      drive_sample(r_ar, r_ai, r_br, r_bi);
    end

    @(posedge clk);
    valid_in <= 1'b0;

    // Wait until all outputs are received and checked
    wait (fifo_count == 0);
    #(CLK_PER * 5);

    $display("===========================================");
    $display(" Tests Completed   : %0d", test_count);
    $display(" Errors Encountered: %0d", error_count);
    if (error_count == 0) begin
      $display(" STATUS: >>> TEST PASSED <<<");
    end else begin
      $display(" STATUS: >>> TEST FAILED <<<");
    end
    $display("===========================================");
    $finish;
  end

endmodule

sim/gen/vcd/tb_cmult_20260926_083220.vcd
$date
	Sat Sep 26 08:32:20 2026
$end
$version
	Icarus Verilog
$end
$timescale
	1ps
$end
$scope module tb_cmult $end
$var wire 1 ! valid_out $end
$var wire 16 " p_re [15:0] $end
$var wire 16 # p_im [15:0] $end
$var parameter 32 $ CLK_PER $end
$var parameter 32 % FIFO_DEPTH $end
$var parameter 32 & FRAC_BITS $end
$var real 1 ' SCALE $end
$var parameter 32 ( WIDTH $end
$var reg 16 ) a_im [15:0] $end
$var reg 16 * a_re [15:0] $end
$var reg 16 + b_im [15:0] $end
$var reg 16 , b_re [15:0] $end
$var reg 1 - clk $end
$var reg 1 . rst_n $end
$var reg 1 / valid_in $end
$var integer 32 0 error_count [31:0] $end
$var integer 32 1 fifo_count [31:0] $end
$var integer 32 2 i [31:0] $end
$var integer 32 3 rd_ptr [31:0] $end
$var integer 32 4 test_count [31:0] $end
$var integer 32 5 wr_ptr [31:0] $end
$scope function to_real $end
$upscope $end
$scope module dut $end
$var wire 16 6 a_im [15:0] $end
$var wire 16 7 a_re [15:0] $end
$var wire 16 8 b_im [15:0] $end
$var wire 16 9 b_re [15:0] $end
$var wire 1 - clk $end
$var wire 1 . rst_n $end
$var wire 1 / valid_in $end
$var parameter 32 : FRAC_BITS $end
$var parameter 16 ; MAX_NEG $end
$var parameter 16 < MAX_POS $end
$var parameter 32 = PROD_WIDTH $end
$var parameter 1 > SATURATE $end
$var parameter 32 ? WIDTH $end
$var reg 16 @ a_im_r [15:0] $end
$var reg 16 A a_re_r [15:0] $end
$var reg 16 B b_im_r [15:0] $end
$var reg 16 C b_re_r [15:0] $end
$var reg 32 D m_ii [31:0] $end
$var reg 32 E m_ir [31:0] $end
$var reg 32 F m_ri [31:0] $end
$var reg 32 G m_rr [31:0] $end
$var reg 16 H p_im [15:0] $end
$var reg 16 I p_re [15:0] $end
$var reg 33 J rnd_im [32:0] $end
$var reg 33 K rnd_re [32:0] $end
$var reg 33 L sum_im [32:0] $end
$var reg 33 M sum_re [32:0] $end
$var reg 1 ! valid_out $end
$var reg 1 N vld_pipe_1 $end
$var reg 1 O vld_pipe_2 $end
$scope function saturate_and_slice $end
$upscope $end
$upscope $end
$scope begin $unm_blk_22 $end
$var real 1 P actual_im $end
$var real 1 Q actual_re $end
$var real 1 R diff_im $end
$var real 1 S diff_re $end
$var real 1 T expected_im $end
$var real 1 U expected_re $end
$upscope $end
$scope begin $unm_blk_29 $end
$var real 1 V r_ai $end
$var real 1 W r_ar $end
$var real 1 X r_bi $end
$var real 1 Y r_br $end
$upscope $end
$scope task drive_sample $end
$upscope $end
$scope task push_expected $end
$upscope $end
$upscope $end
$enddefinitions $end
$comment Show the parameter values. $end
$dumpall
b10000 ?
1>
b100000 =
b111111111111111 <
b1000000000000000 ;
b1111 :
b10000 (
r32768 '
b1111 &
b1000000 %
b1010 $
$end
#0
$dumpvars
r0 Y
r0 X
r0 W
r0 V
r0 U
r0 T
r0 S
r0 R
r0 Q
r0 P
xO
xN
bx M
bx L
bx K
bx J
bx I
bx H
bx G
bx F
bx E
bx D
bx C
bx B
bx A
bx @
b0 9
b0 8
b0 7
b0 6
b0 5
b0 4
b0 3
b0 2
b0 1
b0 0
0/
0.
0-
b0 ,
b0 +
b0 *
b0 )
bx #
bx "
x!
$end
#5000
b100000000000000 J
b100000000000000 K
b0 L
b0 M
0N
b0 B
b0 C
b0 @
b0 A
0O
b0 E
b0 F
b0 D
b0 G
0!
b0 #
b0 H
b0 "
b0 I
1-
#10000
0-
#15000
1-
#20000
0-
#25000
1-
#30000
0-
#35000
1-
#40000
0-
#45000
1-
#50000
0-
1.
#55000
1-
#60000
0-
#65000
1-
#70000
0-
#75000
b1100000000000000 +
b1100000000000000 8
b100000000000000 ,
b100000000000000 9
1/
b1 1
b1 5
1-
#80000
0-
#85000
1N
b1100000000000000 B
b100000000000000 C
b0 +
b0 8
b111111111111100 ,
b111111111111100 9
b1110000000000000 )
b1110000000000000 6
b110000000000000 *
b110000000000000 7
b10 1
b10 5
1-
#90000
0-
#95000
1O
b0 B
b111111111111100 C
b1110000000000000 @
b110000000000000 A
b111111111111100 +
b111111111111100 8
b0 ,
b0 9
b10011001100110 )
b10011001100110 6
b100000000000000 *
b100000000000000 7
b11 1
b11 5
1-
#100000
0-
#105000
b111110000000000001100000000000000 J
b101111111111101100000000000000 K
b111110000000000001000000000000000 L
b101111111111101000000000000000 M
b111111111111100 B
b0 C
b10011001100110 @
b100000000000000 A
b11110000000000001000000000000000 E
b101111111111101000000000000000 G
1!
b0 +
b0 8
b1000000000000000 ,
b1000000000000000 9
b0 )
b0 6
b1000000000000000 *
b1000000000000000 7
b100 1
b100 5
1-
#110000
0-
#115000
b11111111111110100000000000000 J
b111101100110011011101100110011000 K
b11111111111110000000000000000 L
b111101100110011011001100110011000 M
b1110000000000001 #
b1110000000000001 H
b101111111111101 "
b101111111111101 I
b0 E
b11111111111110000000000000000 F
b10011001100100110011001101000 D
b0 G
b0 B
b1000000000000000 C
b0 @
b1000000000000000 A
0/
b1 4
b11 1
b1 3
1-
#120000
0-
#125000
b100000000000000 J
b1000000000000000100000000000000 K
b0 L
b1000000000000000000000000000000 M
0N
b0 F
b0 D
b1000000000000000000000000000000 G
b11111111111110 #
b11111111111110 H
b1101100110011011 "
b1101100110011011 I
b10 4
r5.517578125002753e-06 R
r1.655273437495275e-05 S
r-0.249969482421875 P
r0.749908447265625 Q
b10 1
b10 3
r-0.249975 T
r0.749925 U
1-
#130000
0-
#135000
b0 #
b0 H
b111111111111111 "
b111111111111111 I
0O
b11 4
r1.103515625000551e-05 R
r1.272460937501441e-05 S
r0.49993896484375 P
r-0.299957275390625 Q
b1 1
b11 3
r0.49995 T
r-0.29997 U
1-
#140000
0-
#145000
0!
b100 4
r-0 R
r0 S
r0 P
r0.999969482421875 Q
b0 1
b100 3
r-0 T
r0.999969482421875 U
1-
#150000
0-
#155000
1-
#160000
0-
#165000
b1011000111110000 +
b1011000111110000 8
b1000010010000100 ,
b1000010010000100 9
b1100000010001001 )
b1100000010001001 6
b1001000010101 *
b1001000010101 7
1/
b1 2
b1 1
b101 5
1-
r-0.928009033203125 X
r-0.60345458984375 Y
r0.553680419921875 V
r0.052520751953125 W
#170000
0-
#175000
1N
b1011000111110000 B
b1000010010000100 C
b1100000010001001 @
b1001000010101 A
b1000100100110111 +
b1000100100110111 8
b1011001011000010 ,
b1011001011000010 9
b100011011011111 )
b100011011011111 6
b11010111001 *
b11010111001 7
r0.238677978515625 X
r0.462005615234375 Y
r0.053436279296875 V
r0.007415771484375 W
b10 2
b10 1
b110 5
1-
#180000
0-
#185000
b11001000110011010001101010100 J
b111100011111011010010110101100100 K
b11001000110010110001101010100 L
b111100011111011001110110101100100 M
b1000100100110111 B
b1011001011000010 C
b100011011011111 @
b11010111001 A
1O
b11110100111001110101010100100 E
b11111010011111000111100010110000 F
b10011010110100011100101110000 D
b11110111010001110010011011010100 G
b1111010001101 +
b1111010001101 8
b11101100100011 ,
b11101100100011 9
b11011010111 )
b11011010111 6
b11110011 *
b11110011 7
r-0.224884033203125 X
r0.976470947265625 Y
r0.548248291015625 V
r0.9283447265625 W
b11 2
b11 1
b111 5
1-
#190000
0-
#195000
b111100111011111110111010110111101 J
b11110110110110110100101001001 K
b111100111011111110011010110111101 L
b11110110110110010100101001001 M
1!
b11001000110011 #
b11001000110011 H
b1100011111011010 "
b1100011111011010 I
b11101010100111011100001011111110 E
b11111100111000010111001010111111 F
b11011111000111011001000011101001 D
b11111101111110001011101000110010 G
b1111010001101 B
b11101100100011 C
b11011010111 @
b11110011 A
b1110001100110111 +
b1110001100110111 8
b111110011111101 ,
b111110011111101 9
b100011000101101 )
b100011000101101 6
b111011011010100 *
b111011011010100 7
r-0.53265380859375 X
r0.895965576171875 Y
r-0.335357666015625 V
r-0.226837158203125 W
b100 2
b100 1
b1000 5
1-
#200000
0-
#205000
b1101100011011110000111100 J
b111111111011001110110101111001110 K
b1101100010111110000111100 L
b111111111011001110010101111001110 M
b1110001100110111 B
b111110011111101 C
b100011000101101 @
b111011011010100 A
b1100101000111110001100101 E
b111001111111111010111 F
b110100001111011001101011 D
b1110000010001000111001 G
b1100111011111110 #
b1100111011111110 H
b11110110110110 "
b11110110110110 I
b1011101111010010 +
b1011101111010010 8
b111001010101111 ,
b111001010101111 9
b1101010100010011 )
b1101010100010011 6
b1110001011110111 *
b1110001011110111 7
r-0.19171142578125 X
r0.94677734375 Y
r0.5618896484375 V
r-0.92816162109375 W
b101 2
b1001 5
b101 4
r6.835907697677612e-06 R
r4.43682074546814e-06 S
r0.392181396484375 P
r-0.43865966796875 Q
b100 1
b101 3
r0.3921745605766773 T
r-0.4386641047894955 U
1-
#210000
0-
#215000
b10100111001101110101000000101 J
b1000001111010000110010011011001 K
b10100111001101010101000000101 L
b1000001111010000010010011011001 M
b1101100011 #
b1101100011 H
b1111111011001110 "
b1111111011001110 I
b100010010000110010011001111001 E
b11110010101000111000001110001100 F
b11111000000110111111101010101011 D
b111010000001000001111110000100 G
b1011101111010010 B
b111001010101111 C
b1101010100010011 @
b1110001011110111 A
b1110011101110110 +
b1110011101110110 8
b111100100110000 ,
b111100100110000 9
b100011111101100 )
b100011111101100 6
b1000100100110010 *
b1000100100110010 7
r-0.26129150390625 X
r0.362060546875 Y
r-0.22821044921875 V
r-0.09375 W
b110 2
b1010 5
b110 4
r1.281220465898514e-05 R
r9.843148291110992e-06 S
r-0.38287353515625 P
r0.48211669921875 Q
b100 1
b110 3
r-0.382860722951591 T
r0.4821265423670411 U
1-
#220000
0-
#225000
b111110100100000001111100110011011 J
b111100111100011111011101001000011 K
b111110100100000001011100110011011 L
b111100111100011110111101001000011 M
b1110011101110110 B
b111100100110000 C
b100011111101100 @
b1000100100110010 A
b11101100110001010001110111111101 E
b111101110111001101110011110 F
b1011011011101010101010010110 D
b11110010111111100010010011011001 G
b10100111001101 #
b10100111001101 H
b111111111111111 "
b111111111111111 I
b1101111010001110 +
b1101111010001110 8
b10111001011000 ,
b10111001011000 9
b1110001011001010 )
b1110001011001010 6
b1111010000000000 *
b1111010000000000 7
r0.042572021484375 X
r-0.609893798828125 Y
r-0.604278564453125 V
r-0.822906494140625 W
b111 2
b1011 5
b111 4
r8.977949619293213e-07 R
r1.044385135173798e-05 S
r0.026458740234375 P
r-0.00933837890625 Q
b100 1
b111 3
r0.02645784243941307 T
r-0.009327935054898262 U
1-
#230000
0-
#235000
b101101011011111010001101001100 J
b111001110101001111000000010011000 K
b101101011011110110001101001100 L
b111001110101001110100000010011000 M
b1110100100000001 #
b1110100100000001 H
b1100111100011111 "
b1100111100011111 I
b100010000011000000100001000000 E
b1011011000110101101100001100 F
b11111001000110110001101011001000 D
b11000111110000100101101101100000 G
b1101111010001110 B
b10111001011000 C
b1110001011001010 @
b1111010000000000 A
b10101110011 +
b10101110011 8
b1011000111101111 ,
b1011000111101111 9
b1011001010100111 )
b1011001010100111 6
b1001011010101011 *
b1001011010101011 7
r-0.3843994140625 X
r0.667724609375 Y
r0.1280517578125 V
r-0.498199462890625 W
b1000 2
b1100 5
b1000 4
r1.00182369351387e-05 R
r0 S
r0.326568603515625 P
r0.999969482421875 Q
b100 1
b1000 3
r0.3265786217525601 T
r0.999969482421875 U
1-
#240000
0-
#245000
b111111100010001111101100101110000 J
b111111010000000110010011111110100 K
b111111100010001111001100101110000 L
b111111010000000101110011111110100 M
b10101110011 B
b1011000111101111 C
b1011001010100111 @
b1001011010101011 A
b11111010101101100100000101110000 E
b1100100010101100000000000 F
b11110100001111100000001100 D
b11111101110100111110000000000000 G
b101101011011111 #
b101101011011111 H
b1001110101001111 "
b1001110101001111 I
b1100111011001100 +
b1100111011001100 8
b101010101111000 ,
b101010101111000 9
b1000001100100 )
b1000001100100 6
b1100000000111011 *
b1100000000111011 7
r-0.674591064453125 X
r-0.9473876953125 Y
r-0.925689697265625 V
r-0.4130859375 W
b1001 2
b1101 5
b1001 4
r1.373421400785446e-05 R
r1.368112862110138e-06 S
r-0.179656982421875 P
r-0.381866455078125 Q
b100 1
b1001 3
r-0.1796432482078671 T
r-0.3818678231909871 U
1-
#250000
0-
#255000
b10101010110001000011010111010 J
b100001110001001010000010100000 K
b10101010110000100011010111010 L
b100001110001000110000010100000 M
b1111100010001111 #
b1111100010001111 H
b1111010000000110 "
b1111010000000110 I
b10111100101100100000011101001 E
b11111101110000100000010111010001 F
b11111110010110101000010000000101 D
b100000000111101110010010100101 G
b1100111011001100 B
b101010101111000 C
b1000001100100 @
b1100000000111011 A
b1010100110100111 +
b1010100110100111 8
b1000011010111100 ,
b1000011010111100 9
b1000100110000011 )
b1000100110000011 6
b1100101100100000 *
b1100101100100000 7
r-0.31768798828125 X
r-0.991485595703125 Y
r-0.16680908203125 V
r0.418914794921875 W
b1010 2
b1110 5
b1010 4
r6.843358278274536e-06 R
r1.511722803115845e-05 S
r0.709930419921875 P
r-0.771026611328125 Q
b100 1
b1010 3
r0.7099235765635967 T
r-0.7710417285561562 U
1-
#260000
0-
#265000
b10001101110101100101111100100 J
b111101101110111000110101011111000 K
b10001101110101000101111100100 L
b111101101110111000010101011111000 M
b1010100110100111 B
b1000011010111100 C
b1000100110000011 @
b1100101100100000 A
b101011110001110001011100000 E
b1100010000011010100100000100 F
b11111100110110011000011110110000 D
b11101010101101011011001010101000 G
b10101010110001 #
b10101010110001 H
b100001110001001 "
b100001110001001 I
b1101011101010110 +
b1101011101010110 8
b1000000100010111 ,
b1000000100010111 9
b1110101010100110 )
b1110101010100110 6
b11010110011111 *
b11010110011111 7
r0.039337158203125 X
r0.1368408203125 Y
r-0.189300537109375 V
r0.117156982421875 W
b1011 2
b1111 5
b1011 4
r6.064772605895996e-06 R
r5.733221769332886e-06 S
r-0.058135986328125 P
r-0.09356689453125 Q
b100 1
b1011 3
r-0.0581299215555191 T
r-0.09357262775301933 U
1-
#270000
0-
#275000
b1001001111101100111000000010100 J
b111110001000101001111110000001011 K
b1001001111101100011000000010100 L
b111110001000101001011110000001011 M
b10001101110101 #
b10001101110101 H
b1101101110111000 "
b1101101110111000 I
b111000001000001000111000110100 E
b10001110101011010000111100000 F
b100111111101110010111101110101 D
b11001000010111110101110000000 G
b1101011101010110 B
b1000000100010111 C
b1110101010100110 @
b11010110011111 A
b10100001001 +
b10100001001 8
b1000110000100 ,
b1000110000100 9
b1110011111000101 )
b1110011111000101 6
b111011111111 *
b111011111111 7
r0.54046630859375 X
r0.948486328125 Y
r-0.764129638671875 V
r-0.207427978515625 W
b1100 2
b10000 5
b1100 4
r1.365505158901215e-05 R
r7.480382919311523e-06 S
r0.333526611328125 P
r0.527618408203125 Q
b100 1
b1100 3
r0.333512956276536 T
r0.5276109278202057 U
1-
#280000
0-
#285000
b10000100011000011101010100 J
b111100010000001101111001010000101 K
b10000100010100011101010100 L
b111100010000001101011001010000101 M
b10100001001 B
b1000110000100 C
b1110011111000101 @
b111011111111 A
b1010100101011011101011101010 E
b11110111011110111000110001101010 F
b11011001000011110111000100 D
b11100101011010101111000001001001 G
b111111111111111 #
b111111111111111 H
b1110001000101001 "
b1110001000101001 I
b100010100101110 +
b100010100101110 8
b111100101101000 ,
b111100101101000 9
b1001111000110001 )
b1001111000110001 6
b1110010101110011 *
b1110010101110011 7
r-0.46453857421875 X
r0.4697265625 Y
r-0.153961181640625 V
r0.2559814453125 W
b1101 2
b10001 5
b1101 4
r2.834945917129517e-06 R
r1.024454832077026e-05 S
r0.277008056640625 P
r-0.283447265625 Q
b100 1
b1101 3
r0.2770108915865421 T
r-0.2834370210766792 U
1-
#290000
0-
#295000
b111111110101000110101100010001011 J
b1100000001110101110001111 K
b111111110101000110001100010001011 L
b1100000001010101110001111 M
b10000100011 #
b10000100011 H
b1100010000001101 "
b1100010000001101 I
b11111110010101111001011010010100 E
b10010111000000111110111 F
b11111111100001011111111011101101 D
b1000001101010101001111100 G
b100010100101110 B
b111100101101000 C
b1001111000110001 @
b1110010101110011 A
b1100010010001010 +
b1100010010001010 8
b11110000100000 ,
b11110000100000 9
b1110110001001011 )
b1110110001001011 6
b10000011000100 *
b10000011000100 7
r0.680328369140625 X
r0.775726318359375 Y
r0.71099853515625 V
r0.920074462890625 W
b1110 2
b10010 5
b1110 4
r0 R
r1.431535929441452e-05 S
r0.999969482421875 P
r-0.233123779296875 Q
b100 1
b1110 3
r0.999969482421875 T
r-0.2331094639375806 U
1-
#300000
0-
#305000
b111001010011100001110011010010010 J
b1101110101110010111111101010 K
b111001010011100001010011010010010 L
b1101110101101110111111101010 M
b1100010010001010 B
b11110000100000 C
b1110110001001011 @
b10000011000100 A
b11010001100111010110110011101000 E
b11111000110100110011100110101010 F
b11100101100100011010000111001110 D
b11110011011010001001000110111000 G
b1111110101000110 #
b1111110101000110 H
b1100000001 "
b1100000001 I
b101011100010101 +
b101011100010101 8
b110001101001011 ,
b110001101001011 9
b101101100000010 )
b101101100000010 6
b111010111000101 *
b111010111000101 7
r-0.557891845703125 X
r-0.954376220703125 Y
r0.164520263671875 V
r-0.262054443359375 W
b1111 2
b10011 5
b1111 4
r1.351162791252136e-05 R
r1.204479485750198e-05 S
r0.032318115234375 P
r-0.468353271484375 Q
b100 1
b1111 3
r0.03230460360646248 T
r-0.4683412266895175 U
1-
#310000
0-
#315000
b111110011110000110001011100001000 J
b11000111100111110000010010 K
b111110011110000101101011100001000 L
b11000111100011110000010010 M
b1001010011100001 #
b1001010011100001 H
b1101110101110 "
b1101110101110 I
b11111011010111110001110101100000 E
b11111000011000111011100110101000 F
b100100100111100110001101110 D
b111101100100000100010000000 G
b101011100010101 B
b110001101001011 C
b101101100000010 @
b111010111000101 A
b1011100010010111 +
b1011100010010111 8
b1000010111010111 ,
b1000010111010111 9
b1010100001111 )
b1010100001111 6
b1101111001110101 *
b1101111001110101 7
r0.22674560546875 X
r-0.7672119140625 Y
r0.31207275390625 V
r0.52301025390625 W
b10000 2
b10100 5
b10000 4
r5.851499736309052e-06 R
r1.03851780295372e-05 S
r-0.02130126953125 P
r0.023468017578125 Q
b100 1
b10000 3
r-0.02129541803151369 T
r0.02347840275615454 U
1-
#320000
0-
#325000
b1001011010111000100101110111111 J
b1110101110001100101010001101 K
b1001011010111000000101110111111 L
b1110101110001000101010001101 M
b1011100010010111 B
b1000010111010111 C
b1010100001111 @
b1101111001110101 A
b100011010011000110111110010110 E
b101000000011111001110000101001 F
b11110111101010010010100101010 D
b101101101011011010111110110111 G
b1110011110000110 #
b1110011110000110 H
b11000111100 "
b11000111100 I
b1110100000110 +
b1110100000110 8
b1001110111001100 ,
b1001110111001100 9
b10011111110010 )
b10011111110010 6
b100001011110010 *
b100001011110010 7
r0.8485107421875 X
r0.944122314453125 Y
r0.08331298828125 V
r-0.506744384765625 W
b10001 2
b10101 5
b10001 4
r9.195879101753235e-06 R
r3.835186362266541e-06 S
r-0.836883544921875 P
r0.21624755859375 Q
b100 1
b10001 3
r-0.8368743490427732 T
r0.2162437234073877 U
1-
#330000
0-
#335000
b111111111010011110000100110011100 J
b10101111000011010100101101010 K
b111111111010011101100100110011100 L
b10101111000010110100101101010 M
b111111111111111 #
b111111111111111 H
b1110101110001 "
b1110101110001 I
b11110101111100110111101010011001 E
b1001010110110100111100000011 F
b11111010001000000011001111011001 D
b10000000000011001110101000011 G
b1110100000110 B
b1001110111001100 C
b10011111110010 @
b100001011110010 A
b110110010011100 +
b110110010011100 8
b111100011011001 ,
b111100011011001 9
b101010101010 )
b101010101010 6
b1011111100100011 *
b1011111100100011 7
r0.560333251953125 X
r0.622100830078125 Y
r0.298492431640625 V
r0.383880615234375 W
b10010 2
b10110 5
b10010 4
r9.767711162567139e-06 R
r1.432187855243683e-05 S
r-0.19122314453125 P
r0.0487060546875 Q
b100 1
b10010 3
r-0.1912329122424126 T
r0.04872037656605244 U
1-
#340000
0-
